aduib_rpc/__init__.py
aduib_rpc/types.py
aduib_rpc/client/__init__.py
aduib_rpc/client/base_client.py
aduib_rpc/client/call_options.py
aduib_rpc/client/client_factory.py
aduib_rpc/client/config.py
aduib_rpc/client/errors.py
aduib_rpc/client/midwares.py
aduib_rpc/client/pool.py
aduib_rpc/client/retry.py
aduib_rpc/client/service_resolver.py
aduib_rpc/client/auth/__init__.py
aduib_rpc/client/auth/credentials.py
aduib_rpc/client/auth/interceptor.py
aduib_rpc/client/transports/__init__.py
aduib_rpc/client/transports/base.py
aduib_rpc/client/transports/grpc.py
aduib_rpc/client/transports/jsonrpc.py
aduib_rpc/client/transports/rest.py
aduib_rpc/discover/__init__.py
aduib_rpc/discover/entities/__init__.py
aduib_rpc/discover/entities/service_instance.py
aduib_rpc/discover/load_balance/__init__.py
aduib_rpc/discover/load_balance/load_balance.py
aduib_rpc/discover/load_balance/load_balance_factory.py
aduib_rpc/discover/registry/__init__.py
aduib_rpc/discover/registry/in_memory.py
aduib_rpc/discover/registry/registry_factory.py
aduib_rpc/discover/registry/service_registry.py
aduib_rpc/discover/registry/nacos/client.py
aduib_rpc/discover/registry/nacos/nacos.py
aduib_rpc/discover/service/__init__.py
aduib_rpc/discover/service/a2a_service_factory.py
aduib_rpc/discover/service/aduibrpc_service_factory.py
aduib_rpc/discover/service/service_factory.py
aduib_rpc/grpc/__init__.py
aduib_rpc/grpc/aduib_rpc_pb2.py
aduib_rpc/grpc/aduib_rpc_pb2.pyi
aduib_rpc/grpc/aduib_rpc_pb2_grpc.py
aduib_rpc/proto/aduib_rpc.proto
aduib_rpc/proto/aduib_rpc.thrift
aduib_rpc/rpc/__init__.py
aduib_rpc/rpc/methods.py
aduib_rpc/server/__init__.py
aduib_rpc/server/context.py
aduib_rpc/server/protocols/__init__.py
aduib_rpc/server/protocols/rest/__init__.py
aduib_rpc/server/protocols/rest/fastapi_app.py
aduib_rpc/server/protocols/rpc/__init__.py
aduib_rpc/server/protocols/rpc/fastapi_app.py
aduib_rpc/server/protocols/rpc/jsonrpc_app.py
aduib_rpc/server/protocols/rpc/starlette_app.py
aduib_rpc-1.0.21.dist-info/METADATA
aduib_rpc-1.0.21.dist-info/WHEEL
aduib_rpc-1.0.21.dist-info/licenses/LICENSE
aduib_rpc-1.0.21.dist-info/RECORD
