Metadata-Version: 2.4
Name: aduib-rpc
Version: 1.0.21
Summary: Aduib RPC - A Python library for Aduib AI RPC framework.
Project-URL: homepage, https://github.com/chaorenex1/aduib_rpc
Project-URL: repository, https://github.com/chaorenex1/aduib_rpc
Project-URL: changelog, https://github.com/chaorenex1/aduib_rpc/blob/main/CHANGELOG.md
Project-URL: documentation, https://github.com/chaorenex1/aduib_rpc
Author-email: chaorenex1 <24537608z@gmail.com>
License: Apache-2.0
License-File: LICENSE
Classifier: Intended Audience :: Developers
Classifier: License :: OSI Approved :: Apache Software License
Classifier: Operating System :: OS Independent
Classifier: Programming Language :: Python
Classifier: Programming Language :: Python :: 3
Classifier: Programming Language :: Python :: 3.12
Classifier: Topic :: Software Development :: Libraries :: Python Modules
Requires-Python: <3.13,>=3.10
Requires-Dist: cryptography>=43.0.0
Requires-Dist: fastapi>=0.115.2
Requires-Dist: grpcio-reflection>=1.66.1
Requires-Dist: grpcio-tools>=1.66.1
Requires-Dist: grpcio>=1.66.1
Requires-Dist: httpx-sse>=0.4.0
Requires-Dist: httpx>=0.28.1
Requires-Dist: protobuf>=4.24.3
Requires-Dist: pydantic>=2.11.0
Requires-Dist: sse-starlette
Requires-Dist: starlette>=0.48.0
Requires-Dist: thrift
Provides-Extra: a2a
Requires-Dist: a2a-sdk>=0.2.4; extra == 'a2a'
Provides-Extra: nacos
Requires-Dist: nacos-sdk-python>2.0.1; extra == 'nacos'
Provides-Extra: telemetry
Requires-Dist: opentelemetry-api>=1.33.0; extra == 'telemetry'
Requires-Dist: opentelemetry-exporter-otlp>=1.33.0; extra == 'telemetry'
Requires-Dist: opentelemetry-instrumentation-asgi>=0.54b0; extra == 'telemetry'
Requires-Dist: opentelemetry-instrumentation-fastapi>=0.54b0; extra == 'telemetry'
Requires-Dist: opentelemetry-instrumentation-grpc>=0.54b0; extra == 'telemetry'
Requires-Dist: opentelemetry-instrumentation-httpx>=0.54b0; extra == 'telemetry'
Requires-Dist: opentelemetry-sdk>=1.33.0; extra == 'telemetry'
Provides-Extra: uvicorn
Requires-Dist: uvicorn>=0.1.5; extra == 'uvicorn'
